gautomator/__init__.py
gautomator/abstract_game_event.py
gautomator/by.py
gautomator/click_type.py
gautomator/context.py
gautomator/element_type.py
gautomator/game_actor.py
gautomator/game_element.py
gautomator/game_element_finder.py
gautomator/game_event_manager.py
gautomator/game_event_type.py
gautomator/gautomator.py
gautomator/common/const.py
gautomator/common/exceptions.py
gautomator/protocol/actor.py
gautomator/protocol/common.py
gautomator/protocol/slate.py
gautomator/protocol/touch.py
gautomator/protocol/umg.py
gautomator/reflect/game_method.py
gautomator/reflect/reflection.py
gautomator/tcp/ga_sdk_client.py
gautomator-1.0.13.dist-info/METADATA
gautomator-1.0.13.dist-info/WHEEL
gautomator-1.0.13.dist-info/top_level.txt
gautomator-1.0.13.dist-info/RECORD
