Metadata-Version: 2.4
Name: gautomator
Version: 1.0.13
Author: Tencent WeTest
Author-email: WeTest@wetest.net
Requires-Python: >=3.6
Requires-Dist: lxml>=4.6.1
Requires-Dist: wetest-osplatform>=0.0.3
Requires-Dist: adbutils!=2.8.*,>=2.8.0
Requires-Dist: tidevice
Requires-Dist: facebook-wda
Requires-Dist: uiautomator2
Dynamic: author
Dynamic: author-email
Dynamic: description
Dynamic: description-content-type
Dynamic: requires-dist
Dynamic: requires-python
